.coveragerc
.editorconfig
.gitignore
.travis.yml
AUTHORS.rst
CONTRIBUTING.rst
HISTORY.rst
LICENSE
MANIFEST.in
Makefile
README.rst
manage.py
requirements.txt
requirements_dev.txt
requirements_test.txt
runtests.py
setup.cfg
setup.py
tox.ini
.github/ISSUE_TEMPLATE.md
django_isnull_list_filter.egg-info/PKG-INFO
django_isnull_list_filter.egg-info/SOURCES.txt
django_isnull_list_filter.egg-info/dependency_links.txt
django_isnull_list_filter.egg-info/not-zip-safe
django_isnull_list_filter.egg-info/top_level.txt
docs/Makefile
docs/authors.rst
docs/conf.py
docs/contributing.rst
docs/history.rst
docs/index.rst
docs/installation.rst
docs/make.bat
docs/readme.rst
docs/usage.rst
isnull_filter/__init__.py
isnull_filter/locale/cs/LC_MESSAGES/django.mo
isnull_filter/locale/cs/LC_MESSAGES/django.po
tests/__init__.py
tests/models.py
tests/settings.py
tests/test_filter.py