Metadata-Version: 1.1
Name: django-isnull-list-filter
Version: 0.2.0
Summary: Simple list_filter that offers filtering by __isnull.
Home-page: https://github.com/PetrDlouhy/django-isnull-list-filter
Author: Petr Dlouhý
Author-email: petr.dlouhy@email.cz
License: MIT
Keywords: django-isnull-list-filter
Platform: UNKNOWN
Classifier: Development Status :: 3 - Alpha
Classifier: Framework :: Django
Classifier: Framework :: Django :: 1.8
Classifier: Framework :: Django :: 1.9
Classifier: Framework :: Django :: 1.10
Classifier: Intended Audience :: Developers
Classifier: License :: OSI Approved :: BSD License
Classifier: Natural Language :: English
Classifier: Programming Language :: Python :: 2
Classifier: Programming Language :: Python :: 2.7
Classifier: Programming Language :: Python :: 3
Classifier: Programming Language :: Python :: 3.3
Classifier: Programming Language :: Python :: 3.4
Classifier: Programming Language :: Python :: 3.5
